compton/__init__.py
compton/common.py
compton/consumer.py
compton/orchestrator.py
compton/provider.py
compton/py.typed
compton/reducer.py
compton-5.0.1.dist-info/licenses/LICENSE
compton-5.0.1.dist-info/METADATA
compton-5.0.1.dist-info/WHEEL
compton-5.0.1.dist-info/top_level.txt
compton-5.0.1.dist-info/RECORD
