Metadata-Version: 2.4
Name: compton
Version: 5.0.1
Summary: An abstract data flow framework for quantitative trading
Author-email: Kael Zhang <i+pypi@kael.me>
Project-URL: Homepage, https://github.com/kaelzhang/python-compton
Project-URL: Repository, https://github.com/kaelzhang/python-compton.git
Keywords: compton,dataflow,quant,quantitative,trading,stock
Classifier: Topic :: Software Development :: Libraries :: Python Modules
Classifier: Programming Language :: Python :: 3.7
Classifier: Programming Language :: Python :: 3.8
Classifier: Programming Language :: Python :: 3.9
Classifier: Programming Language :: Python :: 3.10
Classifier: Programming Language :: Python :: 3.11
Classifier: Programming Language :: Python :: 3.12
Classifier: Programming Language :: Python :: Implementation :: PyPy
Requires-Python: >=3.7
License-File: LICENSE
Provides-Extra: dev
Requires-Dist: pytest>=7.0; extra == "dev"
Requires-Dist: pytest-cov>=4.0; extra == "dev"
Requires-Dist: pytest-asyncio>=0.21.0; extra == "dev"
Requires-Dist: ruff>=0.1.0; extra == "dev"
Requires-Dist: mypy>=1.0; extra == "dev"
Dynamic: license-file
